check_library.py
check_library-1.0.1.dist-info/METADATA
check_library-1.0.1.dist-info/WHEEL
check_library-1.0.1.dist-info/entry_points.txt
check_library-1.0.1.dist-info/top_level.txt
check_library-1.0.1.dist-info/RECORD
