Metadata-Version: 2.1
Name: check-library
Version: 1.0.1
Summary: UNKNOWN
Home-page: UNKNOWN
License: UNKNOWN
Platform: UNKNOWN
Requires-Dist: requests
